motical/__init__.py
motical/aux/__init__.py
motical/aux/who.py
motical/data/__init__.py
motical/data/health.py
motical-0.1.0.dist-info/LICENSE.md
motical-0.1.0.dist-info/WHEEL
motical-0.1.0.dist-info/METADATA
motical-0.1.0.dist-info/RECORD
