Metadata-Version: 2.1
Name: motical
Version: 0.1.0
Summary: Motivational Life Calendar
Author: Max Ligus
Author-email: max.ligus@gmail.com
Requires-Python: >=3.8,<4.0
Classifier: Programming Language :: Python :: 3
Classifier: Programming Language :: Python :: 3.10
Classifier: Programming Language :: Python :: 3.8
Classifier: Programming Language :: Python :: 3.9
Requires-Dist: requests (>=2.28.1,<3.0.0)
